mm_aptos/__init__.py
mm_aptos/ans.py
mm_aptos/balance.py
mm_aptos/coin.py
mm_aptos/py.typed
mm_aptos-0.3.0.dist-info/METADATA
mm_aptos-0.3.0.dist-info/WHEEL
mm_aptos-0.3.0.dist-info/RECORD
