Metadata-Version: 2.4
Name: mm-aptos
Version: 0.3.0
Requires-Python: >=3.12
Requires-Dist: mm-crypto-utils>=0.3.0
